openbb_platform_api/__init__.py
openbb_platform_api/assets/default_apps.json
openbb_platform_api/assets/landing_page.html
openbb_platform_api/main.py
openbb_platform_api/query_models.py
openbb_platform_api/response_models.py
openbb_platform_api/utils/__init__.py
openbb_platform_api/utils/api.py
openbb_platform_api/utils/openapi.py
openbb_platform_api/utils/widgets.py
openbb_platform_api-1.2.1.dist-info/METADATA
openbb_platform_api-1.2.1.dist-info/WHEEL
openbb_platform_api-1.2.1.dist-info/entry_points.txt
openbb_platform_api-1.2.1.dist-info/RECORD
