Metadata-Version: 2.4
Name: openbb-platform-api
Version: 1.2.1
Summary: OpenBB Platform API: Launch script and widgets builder for the OpenBB Platform API and Workspace Backend Connector.
License: AGPL-3.0-only
Author: OpenBB
Author-email: hello@openbb.co
Requires-Python: >=3.9.21,<3.14
Classifier: License :: OSI Approved :: GNU Affero General Public License v3
Classifier: Programming Language :: Python :: 3
Classifier: Programming Language :: Python :: 3.10
Classifier: Programming Language :: Python :: 3.11
Classifier: Programming Language :: Python :: 3.12
Classifier: Programming Language :: Python :: 3.13
Requires-Dist: deepdiff (>=8.6.1)
Requires-Dist: openbb-core (>=1.5.1,<2.0.0)
Project-URL: Documentation, https://docs.openbb.co
Project-URL: Homepage, https://openbb.co
Project-URL: Repository, https://github.com/openbb-finance/openbb
